pal/__init__.py
pal/analysis.py
pal/params.py
pal/portfolio.py
pal/utils.py
tests/__init__.py
tests/desired.py
tests/test_analysis.py
tests/test_portfolio.py
tests/test_utils.py
tests/data/BRK-A.csv
tests/data/F-F_Research_Data_Factors_m.csv
tests/data/Portfolios_Formed_on_ME_monthly_EW.csv
tests/data/__init__.py
tests/data/brka_d_ret.csv
tests/data/edhec-hedgefundindices.csv
tests/data/ind30_m_ew_rets.csv
tests/data/ind30_m_nfirms.csv
tests/data/ind30_m_size.csv
tests/data/ind30_m_vw_rets.csv
tests/data/ind49_m_ew_rets.csv
tests/data/ind49_m_nfirms.csv
tests/data/ind49_m_size.csv
tests/data/ind49_m_vw_rets.csv
tests/data/sample_prices.csv
portfolio_analysis_library-0.0.8.dist-info/LICENSE
portfolio_analysis_library-0.0.8.dist-info/METADATA
portfolio_analysis_library-0.0.8.dist-info/WHEEL
portfolio_analysis_library-0.0.8.dist-info/top_level.txt
portfolio_analysis_library-0.0.8.dist-info/RECORD
