Metadata-Version: 2.1
Name: portfolio-analysis-library
Version: 0.0.8
Summary: #WIP: Analysing Stock Returns & Constructing Portfolios with Python
Home-page: https://github.com/rezan21/Portfolio-Analysis-Library
Author: Reza N
Author-email: 32329310+rezan21@users.noreply.github.com
License: UNKNOWN
Platform: UNKNOWN
Classifier: Development Status :: 1 - Planning
Classifier: Programming Language :: Python :: 3
Classifier: Programming Language :: Python :: 3.6
Classifier: Programming Language :: Python :: 3.7
Classifier: Programming Language :: Python :: 3.8
Classifier: Programming Language :: Python :: 3.9
Classifier: License :: OSI Approved :: MIT License
Classifier: Operating System :: OS Independent
Classifier: Topic :: Utilities
Classifier: Topic :: Office/Business :: Financial :: Investment
Classifier: Intended Audience :: Science/Research
Classifier: Intended Audience :: Financial and Insurance Industry
Requires-Python: >=3.6
License-File: LICENSE
Requires-Dist: pandas (==1.3.4)
Requires-Dist: numpy (==1.21.4)
Requires-Dist: black (==21.11b1)
Requires-Dist: isort (==5.10.1)
Requires-Dist: pylint (==2.11.1)
Requires-Dist: scipy (==1.7.3)
Requires-Dist: twine
Requires-Dist: matplotlib
Requires-Dist: seaborn
Requires-Dist: pytest
Requires-Dist: check-manifest
Provides-Extra: dev
Requires-Dist: pandas (==1.3.4) ; extra == 'dev'
Requires-Dist: numpy (==1.21.4) ; extra == 'dev'
Requires-Dist: black (==21.11b1) ; extra == 'dev'
Requires-Dist: isort (==5.10.1) ; extra == 'dev'
Requires-Dist: pylint (==2.11.1) ; extra == 'dev'
Requires-Dist: scipy (==1.7.3) ; extra == 'dev'
Requires-Dist: twine ; extra == 'dev'
Requires-Dist: matplotlib ; extra == 'dev'
Requires-Dist: seaborn ; extra == 'dev'
Requires-Dist: pytest ; extra == 'dev'
Requires-Dist: check-manifest ; extra == 'dev'
